nomad_openbis/__init__.py
nomad_openbis/openbis.py
pybis/__init__.py
pybis/attachment.py
pybis/attribute.py
pybis/data_set.py
pybis/dataset.py
pybis/definitions.py
pybis/entity_type.py
pybis/experiment.py
pybis/fast_download.py
pybis/group.py
pybis/material.py
pybis/openbis_object.py
pybis/person.py
pybis/project.py
pybis/property.py
pybis/property_reformatter.py
pybis/pybis.py
pybis/role_assignment.py
pybis/sample.py
pybis/semantic_annotation.py
pybis/space.py
pybis/tag.py
pybis/things.py
pybis/utils.py
pybis/vocabulary.py
pybis/scripts/cli.py
tests/conftest.py
tests/test_dataset.py
tests/test_experiment.py
tests/test_fastdownload.py
tests/test_group.py
tests/test_imports.py
tests/test_material.py
tests/test_openbis.py
tests/test_person.py
tests/test_plugin.py
tests/test_project.py
tests/test_sample.py
tests/test_space.py
tests/test_tag.py
tests/test_vocabulary.py
tests/todo_test_external_dms.py
tests/jenkinstest/__init__.py
tests/jenkinstest/artifactrepository.py
tests/jenkinstest/settings.py
tests/jenkinstest/test.py
tests/jenkinstest/testcase.py
tests/jenkinstest/util.py
tests/testdir/testfile
nomad_openbis-1.0.0.dist-info/LICENSE
nomad_openbis-1.0.0.dist-info/METADATA
nomad_openbis-1.0.0.dist-info/WHEEL
nomad_openbis-1.0.0.dist-info/top_level.txt
nomad_openbis-1.0.0.dist-info/RECORD
