Metadata-Version: 2.1
Name: nomad-openbis
Version: 1.0.0
Summary: Nomad pybis handler
Author: The NOMAD Authors
License: 
Project-URL: Repository, https://github.com/FAIRmat-NFDI/nomad-openbis
Classifier: Intended Audience :: Developers
Classifier: Operating System :: OS Independent
Classifier: Programming Language :: Python
Classifier: Programming Language :: Python :: 3.9
Classifier: Programming Language :: Python :: 3.10
Classifier: Programming Language :: Python :: 3.11
Classifier: Programming Language :: Python :: 3.12
Classifier: License :: OSI Approved :: MIT License
Requires-Python: >=3.9
License-File: LICENSE
Requires-Dist: requests
Requires-Dist: urllib3
Requires-Dist: pandas
Requires-Dist: texttable
Requires-Dist: tabulate
Requires-Dist: python-dateutil
Provides-Extra: dev
Requires-Dist: ruff ; extra == 'dev'
Requires-Dist: pytest ; extra == 'dev'
Requires-Dist: structlog ; extra == 'dev'
